<?xml version="1.0" encoding="UTF-8" ?>

<!DOCTYPE tiles-definitions PUBLIC
       "-//Apache Software Foundation//DTD Tiles Configuration 2.0//EN"
       "http://tiles.apache.org/dtds/tiles-config_2_0.dtd">
<tiles-definitions>
	<definition name="baseLayout" template="/jsp/BaseLayout.jsp">
		<put-attribute name="title" value="" />
		<put-attribute name="header" value="/jsp/Header.jsp" />
		<put-attribute name="menu" value="/jsp/Menu.jsp" />
		<put-attribute name="body" value="" />
		<put-attribute name="anouncement" value="/jsp/Anouncement.jsp"></put-attribute>
		<put-attribute name="news" value="/jsp/News.jsp"></put-attribute>
		<put-attribute name="footer" value="/jsp/Footer.jsp" />
	</definition>

	<definition name="loginLayout" template="/jsp/LoginLayout.jsp">
		<put-attribute name="title" value="" />
		<put-attribute name="header" value="/jsp/Header.jsp" />
		<put-attribute name="body" value="" />
		<put-attribute name="footer" value="/jsp/Footer.jsp" />
	</definition>
	

	<definition name="login" extends="loginLayout">
		<put-attribute name="title" value="Login" />
		<put-attribute name="body" value="/jsp/Login.jsp" />
	</definition>
	
	<definition name="home" extends="baseLayout">
		<put-attribute name="title" value="Home" />
		<put-attribute name="body" value="/jsp/Home.jsp" />
	</definition>
	
	<definition name="grade" extends="baseLayout">
		<put-attribute name="title" value="Grades" />
		<put-attribute name="body" value="/jsp/Grade.jsp" />
	</definition>

	

</tiles-definitions>
